variete/__init__.py
variete/misc.py
variete/vraster.py
variete/vrt/__init__.py
variete/vrt/pixel_functions.py
variete/vrt/raster_bands.py
variete/vrt/sources.py
variete/vrt/vrt.py
variete-0.1.0.dist-info/LICENSE
variete-0.1.0.dist-info/METADATA
variete-0.1.0.dist-info/WHEEL
variete-0.1.0.dist-info/top_level.txt
variete-0.1.0.dist-info/RECORD
