Metadata-Version: 2.1
Name: variete
Version: 0.1.0
Summary: Making lazily evaluated raster operations simple.
Author-email: Erik Mannerfelt <33550973+erikmannerfelt@users.noreply.github.com>
License: BSD 3-Clause License
Project-URL: repository, https://github.com/erikmannerfelt/variete
Keywords: lazy,gdal,rasterio,raster,virtual,geospatial,spatial,operation,dem
Requires-Python: >=3.8
License-File: LICENSE
Requires-Dist: rasterio
Requires-Dist: gdal (>=3.2)
